brynq_sdk_nmbrs/__init__.py
brynq_sdk_nmbrs/absence.py
brynq_sdk_nmbrs/address.py
brynq_sdk_nmbrs/bank.py
brynq_sdk_nmbrs/children.py
brynq_sdk_nmbrs/companies.py
brynq_sdk_nmbrs/contract.py
brynq_sdk_nmbrs/costcenter.py
brynq_sdk_nmbrs/costunit.py
brynq_sdk_nmbrs/days.py
brynq_sdk_nmbrs/debtors.py
brynq_sdk_nmbrs/department.py
brynq_sdk_nmbrs/document.py
brynq_sdk_nmbrs/employee_wage_tax_settings.py
brynq_sdk_nmbrs/employees.py
brynq_sdk_nmbrs/employment.py
brynq_sdk_nmbrs/function.py
brynq_sdk_nmbrs/hours.py
brynq_sdk_nmbrs/leave.py
brynq_sdk_nmbrs/manager.py
brynq_sdk_nmbrs/salaries.py
brynq_sdk_nmbrs/salary_tables.py
brynq_sdk_nmbrs/schedules.py
brynq_sdk_nmbrs/social_insurance.py
brynq_sdk_nmbrs/wage_tax.py
brynq_sdk_nmbrs/wagecomponents.py
brynq_sdk_nmbrs/schemas/__init__.py
brynq_sdk_nmbrs/schemas/absence.py
brynq_sdk_nmbrs/schemas/address.py
brynq_sdk_nmbrs/schemas/bank.py
brynq_sdk_nmbrs/schemas/children.py
brynq_sdk_nmbrs/schemas/company.py
brynq_sdk_nmbrs/schemas/contracts.py
brynq_sdk_nmbrs/schemas/costcenter.py
brynq_sdk_nmbrs/schemas/costunit.py
brynq_sdk_nmbrs/schemas/days.py
brynq_sdk_nmbrs/schemas/debtor.py
brynq_sdk_nmbrs/schemas/department.py
brynq_sdk_nmbrs/schemas/document.py
brynq_sdk_nmbrs/schemas/employees.py
brynq_sdk_nmbrs/schemas/employment.py
brynq_sdk_nmbrs/schemas/function.py
brynq_sdk_nmbrs/schemas/hours.py
brynq_sdk_nmbrs/schemas/leave.py
brynq_sdk_nmbrs/schemas/manager.py
brynq_sdk_nmbrs/schemas/salary.py
brynq_sdk_nmbrs/schemas/schedules.py
brynq_sdk_nmbrs/schemas/social_insurance.py
brynq_sdk_nmbrs/schemas/wage_tax.py
brynq_sdk_nmbrs/schemas/wage_tax_settings.py
brynq_sdk_nmbrs/schemas/wagecomponents.py
brynq_sdk_nmbrs-2.3.4.dev0.dist-info/METADATA
brynq_sdk_nmbrs-2.3.4.dev0.dist-info/WHEEL
brynq_sdk_nmbrs-2.3.4.dev0.dist-info/top_level.txt
brynq_sdk_nmbrs-2.3.4.dev0.dist-info/RECORD
