Metadata-Version: 2.4
Name: brynq_sdk_nmbrs
Version: 2.3.4.dev0
Summary: Nmbrs wrapper from BrynQ
Author: BrynQ
Author-email: support@brynq.com
License: BrynQ License
Requires-Dist: brynq-sdk-brynq<5,>=4
Requires-Dist: pandas<3.0.0,>=2.2.0
Requires-Dist: pydantic<3.0.0,>=2.5.0
Requires-Dist: pandera<1.0.0,>=0.16.0
Requires-Dist: zeep<5.0.0,>=4.0.0
Requires-Dist: brynq-sdk-functions>=2.0.5
Dynamic: author
Dynamic: author-email
Dynamic: description
Dynamic: license
Dynamic: requires-dist
Dynamic: summary
